pygments_pytest.py
pygments_pytest-2.5.0.dist-info/LICENSE
pygments_pytest-2.5.0.dist-info/METADATA
pygments_pytest-2.5.0.dist-info/WHEEL
pygments_pytest-2.5.0.dist-info/entry_points.txt
pygments_pytest-2.5.0.dist-info/top_level.txt
pygments_pytest-2.5.0.dist-info/RECORD
